rpi_switch_mqtt/__init__.py
rpi_switch_mqtt/switcher.py
rpi_switch_mqtt-0.0.3.data/scripts/rpi-switch-mqtt
rpi_switch_mqtt-0.0.3.dist-info/DESCRIPTION.rst
rpi_switch_mqtt-0.0.3.dist-info/METADATA
rpi_switch_mqtt-0.0.3.dist-info/RECORD
rpi_switch_mqtt-0.0.3.dist-info/WHEEL
rpi_switch_mqtt-0.0.3.dist-info/metadata.json
rpi_switch_mqtt-0.0.3.dist-info/top_level.txt
