Metadata-Version: 2.0
Name: rpi-switch-mqtt
Version: 0.0.3
Summary: Use mqtt to control relays connected to raspberry
Home-page: https://github.com/goodfield/rpi-switch-mqtt.git
Author: David Uebelacker
Author-email: david@uebelacker.ch
License: The MIT License (MIT)
Requires-Dist: paho-mqtt
